hercules/__init__.py
hercules/_hooks.py
hercules/_typed_ast.py
hercules/build_info
hercules/env.py
hercules/error.py
hercules/toolchain.py
hercules/tutorial.py
hercules/typing.py
hercules/utils.py
hercules/_ffi/__init__.py
hercules/_ffi/_pyversion.py
hercules/_ffi/_selector.py
hercules/_ffi/base.py
hercules/_ffi/error.py
hercules/_ffi/libinfo.py
hercules/_ffi/registry.py
hercules/_ffi/runtime_ctypes.py
hercules/_ffi/_c_ext/__init__.py
hercules/_ffi/_c_ext/_loader.py
hercules/_ffi/_c_ext/fast_c_api.cc
hercules/_ffi/_c_ext/hercules_script_api.so
hercules/_ffi/_c_ext/matx_script_api.so
hercules/_ffi/_c_ext/object.py
hercules/_ffi/_c_ext/packed_func.py
hercules/_ffi/_c_ext/types.py
hercules/cfg/__init__.py
hercules/cfg/builder.py
hercules/cfg/model.py
hercules/contrib/__init__.py
hercules/contrib/_filelock.py
hercules/contrib/cc.py
hercules/contrib/cpp_extension.py
hercules/contrib/inspect3_9_1_patch.py
hercules/contrib/ndk.py
hercules/contrib/statistic.py
hercules/contrib/tar.py
hercules/contrib/util.py
hercules/extension/__init__.py
hercules/extension/cpp/pytorch/CMakeLists.txt
hercules/extension/cpp/pytorch/src/matx_inc.h
hercules/extension/cpp/pytorch/src/tensor_api.cc
hercules/extension/cpp/pytorch/src/torch_inc.h
hercules/extension/cpp/pytorch/src/torch_infer_op.cc
hercules/extension/cpp/pytorch/src/torch_infer_op.h
hercules/extension/cpp/pytorch/src/torch_model.cc
hercules/extension/cpp/pytorch/src/torch_model.h
hercules/extension/cpp/tensorflow/CMakeLists.txt
hercules/extension/cpp/tensorflow/src/_tensorflow_cc_savedmodel_constants.h
hercules/extension/cpp/tensorflow/src/_tensorflow_cc_savedmodel_reader.h
hercules/extension/cpp/tensorflow/src/_tensorflow_cc_savedmodel_signature_constants.h
hercules/extension/cpp/tensorflow/src/_tensorflow_cc_savedmodel_tag_constants.h
hercules/extension/cpp/tensorflow/src/tf_dataset_callback_op.cc
hercules/extension/cpp/tensorflow/src/tf_dataset_callback_op.h
hercules/extension/cpp/tensorflow/src/tf_infer_op.cc
hercules_jit-0.3.3.dist-info/METADATA
hercules_jit-0.3.3.dist-info/WHEEL
hercules_jit-0.3.3.dist-info/top_level.txt
hercules_jit-0.3.3.dist-info/RECORD
