Metadata-Version: 2.1
Name: hercules-jit
Version: 0.3.3
Summary: Static Python AOT Compiler
Home-page: https://github.com/gottingen/hercules
Author: Hercules Team
Author-email: bohuli2048@gmial.com
Requires-Python: >=3.6
Requires-Dist: numpy (<2.0.0,>=1.6)
Requires-Dist: typed-ast (<2.0.0,>=1.4.2)
Requires-Dist: astpretty (<3.0.0,>=1.0)
Requires-Dist: prettytable (<4.0.0,>=1.0)
